ordeq_sentence_transformers/__init__.py
ordeq_sentence_transformers/_version.py
ordeq_sentence_transformers/sentence_transformer.py
ordeq_sentence_transformers-1.0.2.dist-info/licenses/LICENSE
ordeq_sentence_transformers-1.0.2.dist-info/METADATA
ordeq_sentence_transformers-1.0.2.dist-info/WHEEL
ordeq_sentence_transformers-1.0.2.dist-info/top_level.txt
ordeq_sentence_transformers-1.0.2.dist-info/RECORD
